aseprite_ini/__init__.py
aseprite_ini-0.0.7.dist-info/METADATA
aseprite_ini-0.0.7.dist-info/WHEEL
aseprite_ini-0.0.7.dist-info/licenses/LICENSE
aseprite_ini-0.0.7.dist-info/RECORD
