Metadata-Version: 2.3
Name: aseprite-ini
Version: 0.0.7
Summary: A tool to parse Aseprite '.ini' format file.
Project-URL: homepage, https://github.com/aseprite-quest/aseprite-ini
Project-URL: source, https://github.com/aseprite-quest/aseprite-ini
Project-URL: issues, https://github.com/aseprite-quest/aseprite-ini/issues
Author: Aseprite Quest
Maintainer: Aseprite Quest
License: MIT License
License-File: LICENSE
Keywords: aseprite
Classifier: License :: OSI Approved :: MIT License
Classifier: Operating System :: OS Independent
Classifier: Programming Language :: Python :: 3
Requires-Python: >=3.10
Requires-Dist: requests>=2.31.0
